flowmatic/__init__.py
flowmatic/ast_nodes.py
flowmatic/cli.py
flowmatic/flowmatic.gram
flowmatic/parser.py
flowmatic/examples/block_integrity.flowmatic
flowmatic/examples/inventory_reorder.flowmatic
flowmatic/examples/invoice_generator.flowmatic
flowmatic/examples/payroll.flowmatic
flowmatic/examples/set_operation_demo.flowmatic
flowmatic/examples/univac_21.flowmatic
flowmatic/examples/xi_sections_demo.flowmatic
ian_flowmatic-1.0.1.dist-info/licenses/LICENSE
ian_flowmatic-1.0.1.dist-info/METADATA
ian_flowmatic-1.0.1.dist-info/WHEEL
ian_flowmatic-1.0.1.dist-info/entry_points.txt
ian_flowmatic-1.0.1.dist-info/top_level.txt
ian_flowmatic-1.0.1.dist-info/RECORD
