Metadata-Version: 2.4
Name: ian-flowmatic
Version: 1.0.1
Summary: FLOW-MATIC Interpreter - Grace Hopper's 1957 Business Language
Author-email: The Ian Index <zane@theianindex.com>
Maintainer-email: The Ian Index <zane@theianindex.com>
License: MIT
Project-URL: Homepage, https://github.com/Zaneham/Flow-matic
Project-URL: Documentation, https://github.com/Zaneham/Flow-matic#readme
Project-URL: Repository, https://github.com/Zaneham/Flow-matic.git
Project-URL: Issues, https://github.com/Zaneham/Flow-matic/issues
Project-URL: Changelog, https://github.com/Zaneham/Flow-matic/releases
Keywords: flow-matic,flowmatic,grace-hopper,cobol,univac,programming-language,interpreter,vintage-computing,computer-history,ian-index
Classifier: Development Status :: 5 - Production/Stable
Classifier: Environment :: Console
Classifier: Intended Audience :: Developers
Classifier: Intended Audience :: Education
Classifier: Intended Audience :: Science/Research
Classifier: License :: OSI Approved :: MIT License
Classifier: Operating System :: OS Independent
Classifier: Programming Language :: Python :: 3
Classifier: Programming Language :: Python :: 3.8
Classifier: Programming Language :: Python :: 3.9
Classifier: Programming Language :: Python :: 3.10
Classifier: Programming Language :: Python :: 3.11
Classifier: Programming Language :: Python :: 3.12
Classifier: Topic :: Education
Classifier: Topic :: Scientific/Engineering :: Interface Engine/Protocol Translator
Classifier: Topic :: Software Development :: Interpreters
Classifier: Topic :: System :: Emulators
Requires-Python: >=3.8
License-File: LICENSE
Provides-Extra: dev
Requires-Dist: pytest>=7.0; extra == "dev"
Requires-Dist: pytest-cov>=4.0; extra == "dev"
Requires-Dist: black>=23.0; extra == "dev"
Requires-Dist: mypy>=1.0; extra == "dev"
Dynamic: license-file
